LICENSE
MANIFEST.in
README.txt
buildout.cfg
setup.py
docs/HISTORY.txt
docs/README.txt
src/ztfy/__init__.py
src/ztfy.zmi.egg-info/PKG-INFO
src/ztfy.zmi.egg-info/SOURCES.txt
src/ztfy.zmi.egg-info/dependency_links.txt
src/ztfy.zmi.egg-info/entry_points.txt
src/ztfy.zmi.egg-info/namespace_packages.txt
src/ztfy.zmi.egg-info/not-zip-safe
src/ztfy.zmi.egg-info/requires.txt
src/ztfy.zmi.egg-info/top_level.txt
src/ztfy/zmi/__init__.py
src/ztfy/zmi/configure.zcml
src/ztfy/zmi/layer.py
src/ztfy/zmi/macros.py
src/ztfy/zmi/skin.py
src/ztfy/zmi/doctests/README.txt
src/ztfy/zmi/locales/ztfy.zmi.pot
src/ztfy/zmi/locales/en/LC_MESSAGES/ztfy.zmi.mo
src/ztfy/zmi/locales/en/LC_MESSAGES/ztfy.zmi.po
src/ztfy/zmi/locales/fr/LC_MESSAGES/ztfy.zmi.mo
src/ztfy/zmi/locales/fr/LC_MESSAGES/ztfy.zmi.po
src/ztfy/zmi/templates/form_macros.pt
src/ztfy/zmi/templates/view_macros.pt
src/ztfy/zmi/tests/__init__.py
src/ztfy/zmi/tests/test_zmidocs.py
src/ztfy/zmi/tests/test_zmidocstrings.py
src/ztfy/zmi/viewlets/__init__.py
src/ztfy/zmi/viewlets/actions/__init__.py
src/ztfy/zmi/viewlets/actions/actions.pt
src/ztfy/zmi/viewlets/actions/configure.zcml
src/ztfy/zmi/viewlets/header/__init__.py
src/ztfy/zmi/viewlets/header/configure.zcml
src/ztfy/zmi/viewlets/header/crumbs.pt
src/ztfy/zmi/viewlets/header/crumbs.py